odoo8_addon_mgmtsystem_action-8.0.1.2.3.99.dev4-nspkg.pth
odoo_addons/mgmtsystem_action/__init__.py
odoo_addons/mgmtsystem_action/__openerp__.py
odoo_addons/mgmtsystem_action/action_sequence.xml
odoo_addons/mgmtsystem_action/board_mgmtsystem_action.xml
odoo_addons/mgmtsystem_action/demo_action.xml
odoo_addons/mgmtsystem_action/mgmtsystem_action.py
odoo_addons/mgmtsystem_action/mgmtsystem_action.xml
odoo_addons/mgmtsystem_action/mgmtsystem_action_stage.py
odoo_addons/mgmtsystem_action/mgmtsystem_claim_stage.xml
odoo_addons/mgmtsystem_action/workflow_mgmtsystem_action.xml
odoo_addons/mgmtsystem_action/data/mgmtsystem_action_stage.xml
odoo_addons/mgmtsystem_action/i18n/de.po
odoo_addons/mgmtsystem_action/i18n/es.po
odoo_addons/mgmtsystem_action/i18n/fr.po
odoo_addons/mgmtsystem_action/i18n/hr.po
odoo_addons/mgmtsystem_action/i18n/hu.po
odoo_addons/mgmtsystem_action/i18n/id.po
odoo_addons/mgmtsystem_action/i18n/lv.po
odoo_addons/mgmtsystem_action/i18n/mgmtsystem_action.pot
odoo_addons/mgmtsystem_action/i18n/nb.po
odoo_addons/mgmtsystem_action/i18n/nn.po
odoo_addons/mgmtsystem_action/i18n/pt.po
odoo_addons/mgmtsystem_action/i18n/pt_BR.po
odoo_addons/mgmtsystem_action/i18n/sl.po
odoo_addons/mgmtsystem_action/i18n/sv.po
odoo_addons/mgmtsystem_action/i18n/th.po
odoo_addons/mgmtsystem_action/i18n/vi.po
odoo_addons/mgmtsystem_action/migrations/6.1.1.0/openupgrade_analysis.txt
odoo_addons/mgmtsystem_action/migrations/7.0.1.0/post-migration.py
odoo_addons/mgmtsystem_action/migrations/7.0.1.0/pre-migration.py
odoo_addons/mgmtsystem_action/migrations/8.0.1.0/post-migration.py
odoo_addons/mgmtsystem_action/migrations/8.0.1.0/pre-migration.py
odoo_addons/mgmtsystem_action/security/ir.model.access.csv
odoo_addons/mgmtsystem_action/security/mgmtsystem_action_security.xml
odoo_addons/mgmtsystem_action/static/description/icon.png
odoo_addons/mgmtsystem_action/tests/__init__.py
odoo_addons/mgmtsystem_action/tests/test_create_action.py
odoo_addons/mgmtsystem_action/views/menus.xml
odoo8_addon_mgmtsystem_action-8.0.1.2.3.99.dev4.dist-info/METADATA
odoo8_addon_mgmtsystem_action-8.0.1.2.3.99.dev4.dist-info/WHEEL
odoo8_addon_mgmtsystem_action-8.0.1.2.3.99.dev4.dist-info/namespace_packages.txt
odoo8_addon_mgmtsystem_action-8.0.1.2.3.99.dev4.dist-info/top_level.txt
odoo8_addon_mgmtsystem_action-8.0.1.2.3.99.dev4.dist-info/RECORD
