Metadata-Version: 2.1
Name: odoo8-addon-mgmtsystem-action
Version: 8.0.1.2.3.99.dev4
Summary: Management System - Action
Home-page: http://www.savoirfairelinux.com
Author: Savoir-faire Linux,Odoo Community Association (OCA)
Author-email: support@odoo-community.org
License: AGPL-3
Platform: UNKNOWN
Classifier: Programming Language :: Python
Classifier: Framework :: Odoo
Classifier: License :: OSI Approved :: GNU Affero General Public License v3
Requires-Python: ~=2.7
Requires-Dist: odoo8-addon-mgmtsystem
Requires-Dist: odoo (<9.0a,>=8.0a)
